Workbook

Sheet Dashboard
A1: 🏠 PERSONAL EXPENSE DASHBOARD | May 2025
A2: 💰 Total Spent | D2: 📦 Transactions | G2: 📅 Days Tracked | J2: 📊 Budget Used %
A3: ='Expense Log'!G34 -> 33665 | D3: =COUNTA('Expense Log'!G4:G33) -> 30 | G3: =COUNTA('Daily Summary'!A3:A18) -> 16 | J3: =IFERROR('Expense Log'!G34/SUM('Category Summary'!F3:F10)*100,0) -> 84.1625
A5: 🍔 Top Category | D5: 💳 Fav Payment | G5: 📈 Avg Daily Spend | J5: 💸 Budget Left
A6: =INDEX('Category Summary'!A3:A10,MATCH(MAX('Category Summary'!B3:B10),'Category Summary'!B3:B10,0)) -> Food & Dining | D6: =INDEX('Payment Analysis'!A3:A8,MATCH(MAX('Payment Analysis'!B3:B8),'Payment Analysis'!B3:B8,0)) -> Cash | G6: =IFERROR('Expense Log'!G34/COUNTA('Daily Summary'!A3:A18),0) -> 2104.0625 | J6: =SUM('Category Summary'!G3:G10) -> 6335
A8: CATEGORY BREAKDOWN | F8: 💡 SMART MONEY TIPS ✅ Review your expenses every Sunday ✅ The 50/30/20 Rule: • 50% Needs (food, bills, rent) • 30% Wants (shopping, dining) • 20% Savings & investments ✅ Use UPI for all payments to track easily ✅ Set a daily budget limit and stick to it ✅ Avoid impulse shopping — wait 24 hrs ✅ Collect receipts for all major purchases 📌 Add new expenses to the 'Expense Log' sheet — all summaries update automatically!
A9: Category | B9: Spent | C9: Budget | D9: Status
A10: ='Category Summary'!A5 -> Shopping | B10: ='Category Summary'!B5 -> 5848 | C10: ='Category Summary'!F5 -> 6000 | D10: ='Category Summary'!H5 -> ⚡ Near Limit
A11: ='Category Summary'!A6 -> Entertainment | B11: ='Category Summary'!B6 -> 4380 | C11: ='Category Summary'!F6 -> 4000 | D11: ='Category Summary'!H6 -> ⚠ Over Budget
A12: ='Category Summary'!A7 -> Health & Medical | B12: ='Category Summary'!B7 -> 2020 | C12: ='Category Summary'!F7 -> 3000 | D12: ='Category Summary'!H7 -> ✅ On Track
A13: ='Category Summary'!A8 -> Utilities & Bills | B13: ='Category Summary'!B8 -> 2958 | C13: ='Category Summary'!F8 -> 4000 | D13: ='Category Summary'!H8 -> ✅ On Track
A14: ='Category Summary'!A9 -> Education | B14: ='Category Summary'!B9 -> 2149 | C14: ='Category Summary'!F9 -> 3000 | D14: ='Category Summary'!H9 -> ✅ On Track
A15: ='Category Summary'!A10 -> Others | B15: ='Category Summary'!B10 -> 5430 | C15: ='Category Summary'!F10 -> 7000 | D15: ='Category Summary'!H10 -> ✅ On Track
A16: ='Category Summary'!A11 -> GRAND TOTAL | B16: ='Category Summary'!B11 -> 33665 | C16: ='Category Summary'!F11 -> 40000 | D16: ='Category Summary'!H11 -> 0
A17: ='Category Summary'!A12 -> 0 | B17: ='Category Summary'!B12 -> 0 | C17: ='Category Summary'!F12 -> 0 | D17: ='Category Summary'!H12 -> 0

Sheet Expense Log
A1: 💸 PERSONAL EXPENSE TRACKER | May 2025
A2: Track every rupee — stay in control of your finances
A3: # | B3: Date | C3: Day | D3: Category | E3: Sub-Category / Item | F3: Description | G3: Amount (₹) | H3: Payment Method | I3: Receipt? | J3: Notes
A4: 1 | B4: 01/05/2025 | C4: =IFERROR(TEXT(DATEVALUE(B4),"dddd"),"") -> Sunday | D4: Food & Dining | E4: Groceries | F4: Monthly vegetable & fruit purchase | G4: 1850 | H4: Cash | I4: Yes | J4: Monthly stock
A5: 2 | B5: 01/05/2025 | C5: =IFERROR(TEXT(DATEVALUE(B5),"dddd"),"") -> Sunday | D5: Travel & Fuel | E5: Metro Card Recharge | F5: Monthly metro pass | G5: 500 | H5: UPI | I5: No | J5: —
A6: 3 | B6: 02/05/2025 | C6: =IFERROR(TEXT(DATEVALUE(B6),"dddd"),"") -> Wednesday | D6: Food & Dining | E6: Restaurant | F6: Lunch with colleagues | G6: 680 | H6: Credit Card | I6: Yes | J6: Team lunch
A7: 4 | B7: 02/05/2025 | C7: =IFERROR(TEXT(DATEVALUE(B7),"dddd"),"") -> Wednesday | D7: Travel & Fuel | E7: Petrol | F7: Fuel refill | G7: 1200 | H7: UPI | I7: Yes | J7: Full tank
A8: 5 | B8: 03/05/2025 | C8: =IFERROR(TEXT(DATEVALUE(B8),"dddd"),"") -> Wednesday | D8: Entertainment | E8: Movie Tickets | F8: Weekend movie – 2 tickets | G8: 600 | H8: Debit Card | I8: No | J8: Saturday
A9: 6 | B9: 03/05/2025 | C9: =IFERROR(TEXT(DATEVALUE(B9),"dddd"),"") -> Wednesday | D9: Entertainment | E9: Popcorn & Snacks | F9: Cinema snacks | G9: 280 | H9: Cash | I9: No | J9: —
A10: 7 | B10: 04/05/2025 | C10: =IFERROR(TEXT(DATEVALUE(B10),"dddd"),"") -> Saturday | D10: Utilities & Bills | E10: Electricity Bill | F10: May electricity bill | G10: 1450 | H10: Net Banking | I10: Yes | J10: PSPCL
A11: 8 | B11: 04/05/2025 | C11: =IFERROR(TEXT(DATEVALUE(B11),"dddd"),"") -> Saturday | D11: Utilities & Bills | E11: Internet Bill | F11: Broadband monthly plan | G11: 799 | H11: UPI | I11: Yes | J11: Jio Fiber
A12: 9 | B12: 05/05/2025 | C12: =IFERROR(TEXT(DATEVALUE(B12),"dddd"),"") -> Monday | D12: Health & Medical | E12: Medicine | F12: Blood pressure tablets | G12: 320 | H12: Cash | I12: Yes | J12: Monthly meds
A13: 10 | B13: 05/05/2025 | C13: =IFERROR(TEXT(DATEVALUE(B13),"dddd"),"") -> Monday | D13: Health & Medical | E13: Doctor Visit | F13: General checkup | G13: 500 | H13: Cash | I13: Yes | J13: —
A14: 11 | B14: 06/05/2025 | C14: =IFERROR(TEXT(DATEVALUE(B14),"dddd"),"") -> Thursday | D14: Education | E14: Online Course | F14: Python course subscription | G14: 1299 | H14: Credit Card | I14: Yes | J14: Udemy
A15: 12 | B15: 06/05/2025 | C15: =IFERROR(TEXT(DATEVALUE(B15),"dddd"),"") -> Thursday | D15: Education | E15: Books | F15: Data science books x2 | G15: 850 | H15: Debit Card | I15: Yes | J15: Amazon
... A33: 30 | B33: 16/05/2025 | C33: =IFERROR(TEXT(DATEVALUE(B33),"dddd"),"") | D33: Shopping | E33: Online Shopping | F33: Earbuds purchase | G33: 1599 | H33: Credit Card | I33: Yes | J33: Amazon
A34: TOTAL EXPENSES | G34: =SUM(G4:G33) -> 33665 | H34: =COUNTA(G4:G33) & " transactions" -> 30 transactions

Sheet Category Summary
A1: 📊 EXPENSE SUMMARY BY CATEGORY
A2: Category | B2: Total Spent (₹) | C2: Transactions | D2: Avg per Txn (₹) | E2: % of Total | F2: Budget (₹) | G2: Remaining (₹) | H2: Status
A3: Food & Dining | B3: =SUMIF('Expense Log'!D4:D33,A3,'Expense Log'!G4:G33) -> 6510 | C3: =COUNTIF('Expense Log'!D4:D33,A3) -> 7 | D3: =IF(C3=0,0,B3/C3) -> 930 | E3: =IF('Expense Log'!G34=0,0,B3/'Expense Log'!G34*100) -> 19.337591 | F3: 8000 | G3: =F3-B3 -> 1490 | H3: =IF(G3<0,"⚠ Over Budget",IF(G3<F3*0.1,"⚡ Near Limit","✅ On Track")) -> ✅ On Track
A4: Travel & Fuel | B4: =SUMIF('Expense Log'!D4:D33,A4,'Expense Log'!G4:G33) -> 4370 | C4: =COUNTIF('Expense Log'!D4:D33,A4) -> 5 | D4: =IF(C4=0,0,B4/C4) -> 874 | E4: =IF('Expense Log'!G34=0,0,B4/'Expense Log'!G34*100) -> 12.980841 | F4: 5000 | G4: =F4-B4 -> 630 | H4: =IF(G4<0,"⚠ Over Budget",IF(G4<F4*0.1,"⚡ Near Limit","✅ On Track")) -> ✅ On Track
A5: Shopping | B5: =SUMIF('Expense Log'!D4:D33,A5,'Expense Log'!G4:G33) -> 5848 | C5: =COUNTIF('Expense Log'!D4:D33,A5) -> 3 | D5: =IF(C5=0,0,B5/C5) -> 1949.3333 | E5: =IF('Expense Log'!G34=0,0,B5/'Expense Log'!G34*100) -> 17.371157 | F5: 6000 | G5: =F5-B5 -> 152 | H5: =IF(G5<0,"⚠ Over Budget",IF(G5<F5*0.1,"⚡ Near Limit","✅ On Track")) -> ⚡ Near Limit
A6: Entertainment | B6: =SUMIF('Expense Log'!D4:D33,A6,'Expense Log'!G4:G33) -> 4380 | C6: =COUNTIF('Expense Log'!D4:D33,A6) -> 3 | D6: =IF(C6=0,0,B6/C6) -> 1460 | E6: =IF('Expense Log'!G34=0,0,B6/'Expense Log'!G34*100) -> 13.010545 | F6: 4000 | G6: =F6-B6 -> -380 | H6: =IF(G6<0,"⚠ Over Budget",IF(G6<F6*0.1,"⚡ Near Limit","✅ On Track")) -> ⚠ Over Budget
A7: Health & Medical | B7: =SUMIF('Expense Log'!D4:D33,A7,'Expense Log'!G4:G33) -> 2020 | C7: =COUNTIF('Expense Log'!D4:D33,A7) -> 3 | D7: =IF(C7=0,0,B7/C7) -> 673.33333 | E7: =IF('Expense Log'!G34=0,0,B7/'Expense Log'!G34*100) -> 6.000297 | F7: 3000 | G7: =F7-B7 -> 980 | H7: =IF(G7<0,"⚠ Over Budget",IF(G7<F7*0.1,"⚡ Near Limit","✅ On Track")) -> ✅ On Track
A8: Utilities & Bills | B8: =SUMIF('Expense Log'!D4:D33,A8,'Expense Log'!G4:G33) -> 2958 | C8: =COUNTIF('Expense Log'!D4:D33,A8) -> 4 | D8: =IF(C8=0,0,B8/C8) -> 739.5 | E8: =IF('Expense Log'!G34=0,0,B8/'Expense Log'!G34*100) -> 8.7865736 | F8: 4000 | G8: =F8-B8 -> 1042 | H8: =IF(G8<0,"⚠ Over Budget",IF(G8<F8*0.1,"⚡ Near Limit","✅ On Track")) -> ✅ On Track
A9: Education | B9: =SUMIF('Expense Log'!D4:D33,A9,'Expense Log'!G4:G33) -> 2149 | C9: =COUNTIF('Expense Log'!D4:D33,A9) -> 2 | D9: =IF(C9=0,0,B9/C9) -> 1074.5 | E9: =IF('Expense Log'!G34=0,0,B9/'Expense Log'!G34*100) -> 6.3834843 | F9: 3000 | G9: =F9-B9 -> 851 | H9: =IF(G9<0,"⚠ Over Budget",IF(G9<F9*0.1,"⚡ Near Limit","✅ On Track")) -> ✅ On Track
A10: Others | B10: =SUMIF('Expense Log'!D4:D33,A10,'Expense Log'!G4:G33) -> 5430 | C10: =COUNTIF('Expense Log'!D4:D33,A10) -> 3 | D10: =IF(C10=0,0,B10/C10) -> 1810 | E10: =IF('Expense Log'!G34=0,0,B10/'Expense Log'!G34*100) -> 16.129511 | F10: 7000 | G10: =F10-B10 -> 1570 | H10: =IF(G10<0,"⚠ Over Budget",IF(G10<F10*0.1,"⚡ Near Limit","✅ On Track")) -> ✅ On Track
A11: GRAND TOTAL | B11: =SUM(B3:B10) -> 33665 | C11: =SUM(C3:C10) -> 30 | D11: =IF(C11=0,0,B11/C11) -> 1122.1667 | E11: =100 -> 100 | F11: =SUM(F3:F10) -> 40000 | G11: =SUM(G3:G10) -> 6335

Sheet Daily Summary
A1: 📅 DAILY EXPENSE SUMMARY — May 2025
A2: Date | B2: Day | C2: Total Spent (₹) | D2: Transactions | E2: Highest Single Expense (₹) | F2: Remark
A3: 01/05/2025 | B3: Thursday | C3: =SUMIF('Expense Log'!B4:B33,A3,'Expense Log'!G4:G33) -> 2350 | D3: =COUNTIF('Expense Log'!B4:B33,A3) -> 2 | E3: =IFERROR(maxifs('Expense Log'!G4:G33,'Expense Log'!B4:B33,A3),0) -> 0 | F3: Month start essentials
A4: 02/05/2025 | B4: Friday | C4: =SUMIF('Expense Log'!B4:B33,A4,'Expense Log'!G4:G33) -> 1880 | D4: =COUNTIF('Expense Log'!B4:B33,A4) -> 2 | E4: =IFERROR(maxifs('Expense Log'!G4:G33,'Expense Log'!B4:B33,A4),0) -> 0 | F4: Work day + commute
A5: 03/05/2025 | B5: Saturday | C5: =SUMIF('Expense Log'!B4:B33,A5,'Expense Log'!G4:G33) -> 880 | D5: =COUNTIF('Expense Log'!B4:B33,A5) -> 2 | E5: =IFERROR(maxifs('Expense Log'!G4:G33,'Expense Log'!B4:B33,A5),0) -> 0 | F5: Weekend leisure
A6: 04/05/2025 | B6: Sunday | C6: =SUMIF('Expense Log'!B4:B33,A6,'Expense Log'!G4:G33) -> 2249 | D6: =COUNTIF('Expense Log'!B4:B33,A6) -> 2 | E6: =IFERROR(maxifs('Expense Log'!G4:G33,'Expense Log'!B4:B33,A6),0) -> 0 | F6: Bills day
A7: 05/05/2025 | B7: Monday | C7: =SUMIF('Expense Log'!B4:B33,A7,'Expense Log'!G4:G33) -> 820 | D7: =COUNTIF('Expense Log'!B4:B33,A7) -> 2 | E7: =IFERROR(maxifs('Expense Log'!G4:G33,'Expense Log'!B4:B33,A7),0) -> 0 | F7: Health expenses
A8: 06/05/2025 | B8: Tuesday | C8: =SUMIF('Expense Log'!B4:B33,A8,'Expense Log'!G4:G33) -> 2149 | D8: =COUNTIF('Expense Log'!B4:B33,A8) -> 2 | E8: =IFERROR(maxifs('Expense Log'!G4:G33,'Expense Log'!B4:B33,A8),0) -> 0 | F8: Learning & growth
A9: 07/05/2025 | B9: Wednesday | C9: =SUMIF('Expense Log'!B4:B33,A9,'Expense Log'!G4:G33) -> 4249 | D9: =COUNTIF('Expense Log'!B4:B33,A9) -> 2 | E9: =IFERROR(maxifs('Expense Log'!G4:G33,'Expense Log'!B4:B33,A9),0) -> 0 | F9: Shopping spree
A10: 08/05/2025 | B10: Thursday | C10: =SUMIF('Expense Log'!B4:B33,A10,'Expense Log'!G4:G33) -> 770 | D10: =COUNTIF('Expense Log'!B4:B33,A10) -> 2 | E10: =IFERROR(maxifs('Expense Log'!G4:G33,'Expense Log'!B4:B33,A10),0) -> 0 | F10: Food & commute
A11: 09/05/2025 | B11: Friday | C11: =SUMIF('Expense Log'!B4:B33,A11,'Expense Log'!G4:G33) -> 2160 | D11: =COUNTIF('Expense Log'!B4:B33,A11) -> 2 | E11: =IFERROR(maxifs('Expense Log'!G4:G33,'Expense Log'!B4:B33,A11),0) -> 0 | F11: Fitness + grocery
A12: 10/05/2025 | B12: Saturday | C12: =SUMIF('Expense Log'!B4:B33,A12,'Expense Log'!G4:G33) -> 689 | D12: =COUNTIF('Expense Log'!B4:B33,A12) -> 2 | E12: =IFERROR(maxifs('Expense Log'!G4:G33,'Expense Log'!B4:B33,A12),0) -> 0 | F12: Utilities & misc
A13: 11/05/2025 | B13: Sunday | C13: =SUMIF('Expense Log'!B4:B33,A13,'Expense Log'!G4:G33) -> 660 | D13: =COUNTIF('Expense Log'!B4:B33,A13) -> 2 | E13: =IFERROR(maxifs('Expense Log'!G4:G33,'Expense Log'!B4:B33,A13),0) -> 0 | F13: Work meet + travel
A14: 12/05/2025 | B14: Monday | C14: =SUMIF('Expense Log'!B4:B33,A14,'Expense Log'!G4:G33) -> 5700 | D14: =COUNTIF('Expense Log'!B4:B33,A14) -> 2 | E14: =IFERROR(maxifs('Expense Log'!G4:G33,'Expense Log'!B4:B33,A14),0) -> 0 | F14: Family trip day 1
A15: 13/05/2025 | B15: Tuesday | C15: =SUMIF('Expense Log'!B4:B33,A15,'Expense Log'!G4:G33) -> 1850 | D15: =COUNTIF('Expense Log'!B4:B33,A15) -> 1 | E15: =IFERROR(maxifs('Expense Log'!G4:G33,'Expense Log'!B4:B33,A15),0) -> 0 | F15: Family trip day 2
A16: 14/05/2025 | B16: Wednesday | C16: =SUMIF('Expense Log'!B4:B33,A16,'Expense Log'!G4:G33) -> 410 | D16: =COUNTIF('Expense Log'!B4:B33,A16) -> 2 | E16: =IFERROR(maxifs('Expense Log'!G4:G33,'Expense Log'!B4:B33,A16),0) -> 0 | F16: Routine expenses
A17: 15/05/2025 | B17: Thursday | C17: =SUMIF('Expense Log'!B4:B33,A17,'Expense Log'!G4:G33) -> 5250 | D17: =COUNTIF('Expense Log'!B4:B33,A17) -> 2 | E17: =IFERROR(maxifs('Expense Log'!G4:G33,'Expense Log'!B4:B33,A17),0) -> 0 | F17: Saving + self-care
A18: 16/05/2025 | B18: Friday | C18: =SUMIF('Expense Log'!B4:B33,A18,'Expense Log'!G4:G33) -> 1599 | D18: =COUNTIF('Expense Log'!B4:B33,A18) -> 1 | E18: =IFERROR(maxifs('Expense Log'!G4:G33,'Expense Log'!B4:B33,A18),0) -> 0 | F18: Online shopping
A19: MONTHLY TOTAL | C19: =SUM(C3:C18) -> 33665 | D19: =SUM(D3:D18) -> 30 | E19: =AVERAGE(C3:C18) -> 2104.0625 | F19: Avg daily shown in col E

Sheet Payment Analysis
A1: 💳 PAYMENT METHOD ANALYSIS
A2: Payment Method | B2: Times Used | C2: Total Spent (₹) | D2: Avg Transaction (₹) | E2: % of Spend | F2: % of Count
A3: Cash | B3: =COUNTIF('Expense Log'!H4:H33,A3) -> 11 | C3: =SUMIF('Expense Log'!H4:H33,A3,'Expense Log'!G4:G33) -> 6720 | D3: =IF(B3=0,0,C3/B3) -> 610.90909 | E3: =IF('Expense Log'!G34=0,0,C3/'Expense Log'!G34*100) -> 19.961384 | F3: =IF(SUM(B3:B9)=0,0,B3/SUM(B3:B9)*100) -> 36.666667
A4: UPI | B4: =COUNTIF('Expense Log'!H4:H33,A4) -> 7 | C4: =SUMIF('Expense Log'!H4:H33,A4,'Expense Log'!G4:G33) -> 8907 | D4: =IF(B4=0,0,C4/B4) -> 1272.4286 | E4: =IF('Expense Log'!G34=0,0,C4/'Expense Log'!G34*100) -> 26.457745 | F4: =IF(SUM(B3:B9)=0,0,B4/SUM(B3:B9)*100) -> 23.333333
A5: Credit Card | B5: =COUNTIF('Expense Log'!H4:H33,A5) -> 6 | C5: =SUMIF('Expense Log'!H4:H33,A5,'Expense Log'!G4:G33) -> 9368 | D5: =IF(B5=0,0,C5/B5) -> 1561.3333 | E5: =IF('Expense Log'!G34=0,0,C5/'Expense Log'!G34*100) -> 27.82712 | F5: =IF(SUM(B3:B9)=0,0,B5/SUM(B3:B9)*100) -> 20
A6: Debit Card | B6: =COUNTIF('Expense Log'!H4:H33,A6) -> 2 | C6: =SUMIF('Expense Log'!H4:H33,A6,'Expense Log'!G4:G33) -> 1450 | D6: =IF(B6=0,0,C6/B6) -> 725 | E6: =IF('Expense Log'!G34=0,0,C6/'Expense Log'!G34*100) -> 4.3071439 | F6: =IF(SUM(B3:B9)=0,0,B6/SUM(B3:B9)*100) -> 6.6666667
A7: Net Banking | B7: =COUNTIF('Expense Log'!H4:H33,A7) -> 2 | C7: =SUMIF('Expense Log'!H4:H33,A7,'Expense Log'!G4:G33) -> 6450 | D7: =IF(B7=0,0,C7/B7) -> 3225 | E7: =IF('Expense Log'!G34=0,0,C7/'Expense Log'!G34*100) -> 19.159364 | F7: =IF(SUM(B3:B9)=0,0,B7/SUM(B3:B9)*100) -> 6.6666667
A8: Wallet | B8: =COUNTIF('Expense Log'!H4:H33,A8) -> 2 | C8: =SUMIF('Expense Log'!H4:H33,A8,'Expense Log'!G4:G33) -> 770 | D8: =IF(B8=0,0,C8/B8) -> 385 | E8: =IF('Expense Log'!G34=0,0,C8/'Expense Log'!G34*100) -> 2.2872419 | F8: =IF(SUM(B3:B9)=0,0,B8/SUM(B3:B9)*100) -> 6.6666667
